pidcalib2/__init__.py
pidcalib2/__main__.py
pidcalib2/aliases.py
pidcalib2/argparse_tools.py
pidcalib2/binning.py
pidcalib2/make_eff_hists.py
pidcalib2/markdown_table.py
pidcalib2/merge_trees.py
pidcalib2/pid_data.py
pidcalib2/pklhisto2root.py
pidcalib2/plot_calib_distributions.py
pidcalib2/ref_calib.py
pidcalib2/samples.py
pidcalib2/utils.py
pidcalib2/version.py
pidcalib2/data/samples.json
pidcalib2/tests/__init__.py
pidcalib2/tests/test_binning.py
pidcalib2/tests/test_make_eff_hist.py
pidcalib2/tests/test_merge_trees.py
pidcalib2/tests/test_pid_data.py
pidcalib2/tests/test_pklhisto2root.py
pidcalib2/tests/test_plot_calib_distributions.py
pidcalib2/tests/test_ref_calib.py
pidcalib2/tests/test_ref_calib_ElectronTables.py
pidcalib2/tests/test_samples.py
pidcalib2/tests/test_utils.py
pidcalib2/tests/test_data/cal_test_data.csv
pidcalib2/tests/test_data/cal_test_data.pkl
pidcalib2/tests/test_data/custom_binning.json
pidcalib2/tests/test_data/effhists-2024_WithUT_block1_Tables_2brem-up-e-DLLe>0-P.pkl
pidcalib2/tests/test_data/effhists-2024_WithUT_block8-up-K-DLLK>0.0-P.ETA.nPVs.pkl
pidcalib2/tests/test_data/effhists-Turbo18-up-K-DLLK>0-P-pre1.1.0.pkl
pidcalib2/tests/test_data/effhists-Turbo18-up-K-DLLK>0-P.pkl
pidcalib2/tests/test_data/effhists-Turbo18-up-K-DLLK>4-P.ETA.nTracks.pkl
pidcalib2/tests/test_data/effhists-Turbo18-up-Pi-DLLK<0-P.pkl
pidcalib2/tests/test_data/effhists-Turbo18-up-pi-DLLK<4-P.pkl
pidcalib2/tests/test_data/effhists-test-down-Pi-DLLK>4-P.pkl
pidcalib2/tests/test_data/ref_PID_eff.root
pidcalib2/tests/test_data/ref_test_data.csv
pidcalib2/tests/test_data/ref_test_data.root
pidcalib2/tests/test_data/ref_test_data_ElectronTables.root
pidcalib2/tests/test_data/ref_test_data_run3.root
pidcalib2/tests/test_data/ref_test_data_subdir.root
pidcalib2/tests/test_data/test_file_list
pidcalib2/tests/test_data/test_samples.json
pidcalib2/tests/test_data/sweights_2023/00199935_00000001_1.pid_tuple_sweights.root
pidcalib2-1.4.0.dist-info/LICENSE
pidcalib2-1.4.0.dist-info/METADATA
pidcalib2-1.4.0.dist-info/WHEEL
pidcalib2-1.4.0.dist-info/entry_points.txt
pidcalib2-1.4.0.dist-info/top_level.txt
pidcalib2-1.4.0.dist-info/RECORD
