Metadata-Version: 2.1
Name: pidcalib2
Version: 1.4.0
Summary: A set of tools for estimating LHCb PID efficiencies
Home-page: https://gitlab.cern.ch/lhcb-rta/pidcalib2
Author: Daniel Cervenkov
Author-email: daniel.cervenkov@cern.ch
License: GNU General Public License v3 (GPLv3)
Project-URL: Bug Tracker, https://gitlab.cern.ch/lhcb-rta/pidcalib2/issues
Classifier: License :: OSI Approved :: GNU General Public License v3 (GPLv3)
Classifier: Programming Language :: Python :: 3
Classifier: Operating System :: OS Independent
Requires-Python: >=3.6
License-File: LICENSE
Requires-Dist: boost-histogram
Requires-Dist: lb-telemetry
Requires-Dist: logzero
Requires-Dist: matplotlib
Requires-Dist: mplhep
Requires-Dist: numpy
Requires-Dist: pandas
Requires-Dist: tqdm
Requires-Dist: uproot >=4.2.1
Requires-Dist: xrootd >=5.2
Requires-Dist: apd
